telluric/__init__.py
telluric/_version.py
telluric/base_vrt.py
telluric/collections.py
telluric/constants.py
telluric/context.py
telluric/features.py
telluric/gdalvrt.xsd
telluric/georaster.py
telluric/plotting.py
telluric/rasterization.py
telluric/vectors.py
telluric/vrt.py
telluric/util/__init__.py
telluric/util/general.py
telluric/util/histogram.py
telluric/util/local_tile_server.py
telluric/util/projections.py
telluric/util/raster_utils.py
telluric/util/tileserver_utils.py
telluric-0.14.4.dist-info/LICENSE
telluric-0.14.4.dist-info/METADATA
telluric-0.14.4.dist-info/WHEEL
telluric-0.14.4.dist-info/top_level.txt
telluric-0.14.4.dist-info/RECORD
