Metadata-Version: 2.1
Name: telluric
Version: 0.14.4
Summary: Interactive geospatial data manipulation in Python
Home-page: https://github.com/satellogic/telluric/
Download-URL: https://github.com/satellogic/telluric/tags/v0.14.4
Author: Juan Luis Cano, Guy Doulberg, Slava Kerner, Lucio Torre, Ariel Zerahia, Denis Rykov
Maintainer-email: juanlu@satellogic.com
License: MIT
Classifier: Development Status :: 4 - Beta
Classifier: Intended Audience :: Science/Research
Classifier: License :: OSI Approved :: MIT License
Classifier: Operating System :: OS Independent
Classifier: Programming Language :: Python
Classifier: Programming Language :: Python :: 3
Classifier: Programming Language :: Python :: 3.7
Classifier: Programming Language :: Python :: 3.8
Classifier: Programming Language :: Python :: 3.9
Classifier: Programming Language :: Python :: 3.10
Classifier: Programming Language :: Python :: Implementation :: CPython
Classifier: Topic :: Scientific/Engineering
Classifier: Topic :: Scientific/Engineering :: GIS
Classifier: Topic :: Scientific/Engineering :: Visualization
Requires-Python: >=3.7
License-File: LICENSE
Requires-Dist: affine
Requires-Dist: fiona (<1.9.0,>=1.8.4)
Requires-Dist: shapely (<2.0.0,>=1.6.3)
Requires-Dist: rasterio (>=1.2.0)
Requires-Dist: pillow
Requires-Dist: mercantile (>=0.10.0)
Requires-Dist: boltons
Requires-Dist: imageio
Requires-Dist: lxml
Requires-Dist: python-dateutil
Provides-Extra: dev
Requires-Dist: coverage ; extra == 'dev'
Requires-Dist: mypy ; extra == 'dev'
Requires-Dist: types-python-dateutil ; extra == 'dev'
Requires-Dist: types-pkg-resources ; extra == 'dev'
Requires-Dist: packaging ; extra == 'dev'
Requires-Dist: pycodestyle ; extra == 'dev'
Requires-Dist: pytest (>=4) ; extra == 'dev'
Requires-Dist: pytest-cov (<=2.8.1) ; extra == 'dev'
Requires-Dist: sphinx ; extra == 'dev'
Requires-Dist: ipython ; extra == 'dev'
Requires-Dist: nbsphinx ; extra == 'dev'
Requires-Dist: sphinx-rtd-theme ; extra == 'dev'
Provides-Extra: vis
Requires-Dist: ipyleaflet (!=0.8.2) ; extra == 'vis'
Requires-Dist: matplotlib ; extra == 'vis'
Requires-Dist: folium (>=0.6.0) ; extra == 'vis'
Requires-Dist: tornado ; extra == 'vis'
